Metadata-Version: 2.1
Name: ezipeptpython
Version: 3.0.22
Summary: Python REPL build on top of prompt_toolkit
Home-page: https://github.com/prompt-toolkit/ptpython
Author: Jonathan Slenders
License: UNKNOWN
Platform: UNKNOWN
Classifier: Programming Language :: Python :: 3
Classifier: Programming Language :: Python :: 3.6
Classifier: Programming Language :: Python :: 3.7
Classifier: Programming Language :: Python :: 3.8
Classifier: Programming Language :: Python :: 3 :: Only
Classifier: Programming Language :: Python
Requires-Python: >=3.6
Provides-Extra: ptipython
Provides-Extra: all
